{
  "questions": [
    {
      "id": 1,
      "type": "rating",
      "text": "How satisfied are you with the current state of the Algerian developer ecosystem?",
      "description": "Rate from 1 (very dissatisfied) to 5 (very satisfied).",
      "required": true,
      "option": [1, 2, 3, 4, 5]
    },
    {
      "id": 3,
      "type": "ranking",
      "text": "Rank these programming languages based on your preference.",
      "description": "Drag and drop to reorder. The top one is your most preferred.",
      "required": true,
      "options": [
        { "id": 101, "text": "JavaScript" },
        { "id": 102, "text": "Python" },
        { "id": 103, "text": "Java" },
        { "id": 104, "text": "C#" },
        { "id": 105, "text": "Ruby" }
      ]
    },
    {
      "id": 4,
      "type": "numeric",
      "text": "how do you rate your skills from 1 to 5?",
      "description": "Please rate your skills on a scale of 1 to 5.",
      "required": false
    },

    {
      "id": 5,
      "type": "single_choice",
      "text": "Which frontend framework do you prefer?",
      "description": "Select one that applies",
      "required": true,
      "options": [
        { "id": 201, "text": "React" },
        { "id": 202, "text": "Vue" },
        { "id": 203, "text": "Angular" },
        { "id": 204, "text": "Svelte" }
      ]
    },
    {
      "id": 6,
      "type": "single_choice",
      "text": "Which programming language do you prefer?",
      "description": "Select one that applies",
      "required": true,
      "options": [
        { "id": 201, "text": "JavaScript" },
        { "id": 202, "text": "Python" },
        { "id": 203, "text": "Java" },
        { "id": 204, "text": "C#" },
        { "id": 205, "text": "Ruby" },
        { "id": 206, "text": "Go" },
        { "id": 207, "text": "Rust" },
        { "id": 208, "text": "Kotlin" },
        { "id": 209, "text": "Swift" },
        { "id": 210, "text": "PHP" },
        { "id": 211, "text": "TypeScript" },
        { "id": 212, "text": "C++" },
        { "id": 213, "text": "C" },
        { "id": 214, "text": "Dart" },
        { "id": 215, "text": "Scala" },
        { "id": 216, "text": "Elixir" },
        { "id": 217, "text": "Haskell" },
        { "id": 218, "text": "Perl" },
        { "id": 219, "text": "Lua" }
      ]
    },

    {
      "id": 6,
      "type": "multiple_choice",
      "text": "Which backend technologies do you use? (Select all that apply)",
      "description": "Select at least one",
      "required": true,
      "options": [
        { "id": 301, "text": "Node.js" },
        { "id": 302, "text": "Django" },
        { "id": 303, "text": "Spring Boot" },
        { "id": 304, "text": ".NET Core" }
      ]
    }
  ]
}
